{
    "doors.here_i_come":{"category":"music","sounds":["doors/here_i_come"]},
    "doors.here_i_come_end":{"category":"music","sounds":["doors/here_i_come_end"]},
    "doors.jeffs_jingle":{"category":"music","sounds":["doors/jeffs_jingle"]},
    "doors.dawn_of_the_doors":{"category":"music","sounds":["doors/dawn_of_the_doors"]},
    "doors.dawn_of_the_doors_end":{"category":"music","sounds":["doors/dawn_of_the_doors_end"]},
    "doors.elevator_jam":{"category":"music","sounds":["doors/elevator_jam"]},
    "doors.elevator_jam_end":{"category":"music","sounds":["doors/elevator_jam_end"]},
    "doors.guiding_light":{"category":"music","sounds":["doors/guiding_light"]},
    "doors.guiding_light_end":{"category":"music","sounds":["doors/guiding_light_end"]},
    "doors.unhinged_start":{"category":"music","sounds":["doors/unhinged_start"]},
    "doors.unhinged":{"category":"music","sounds":["doors/unhinged"]},
    "doors.unhinged_end":{"category":"music","sounds":["doors/unhinged_end"]},
    "doors.curious_light":{"category":"music","sounds":["doors/curious_light"]},
    "doors.curious_light_end":{"category":"music","sounds":["doors/curious_light_end"]},
    "doors.dusk_of_the_doors":{"category":"music","sounds":["doors/dusk_of_the_doors"]},
    "doors.dusk_of_the_doors_end":{"category":"music","sounds":["doors/dusk_of_the_doors_end"]},
    "doors.dread":{"category":"music","sounds":["doors/dread"]},
    "doors.dread_end":{"category":"music","sounds":["doors/dread_end"]},
    "doors.elevator_jam_retro_mode":{"category":"music","sounds":["doors/elevator_jam_retro_mode"]},
    "doors.elevator_jam_voiced":{"category":"music","sounds":["doors/elevator_jam_voiced"]},
    "doors.elevator_jammed":{"category":"music","sounds":["doors/elevator_jammed"]},
    "doors.curious_light_door":{"category":"music","sounds":["doors/curious_light_door"]},
    "doors.im_behind_you":{"category":"music","sounds":["doors/im_behind_you"]},
    "doors.unhinged_2":{"category":"music","sounds":["doors/unhinged_2"]},
    "doors.unhinged_2_intense":{"category":"music","sounds":["doors/unhinged_2_intense"]},
    "doors.make_haste":{"category":"music","sounds":["doors/make_haste"]},
    "doors.make_haste_above_1min":{"category":"music","sounds":["doors/make_haste_above_1min"]},
    "doors.make_haste_below_1min":{"category":"music","sounds":["doors/make_haste_below_1min"]},
    "doors.make_haste_below_30s":{"category":"music","sounds":["doors/make_haste_below_30s"]},
    "doors.lever_pull":{"category":"music","sounds":["doors/lever_pull"]},
    "doors.haste_chase":{"category":"music","sounds":["doors/haste_chase"]},
    "doors.haste_near":{"category":"music","sounds":["doors/haste_near"]},

    "doors.elevator_mines":{"category":"music","sounds":["doors/elevator_mines"]},
    "doors.elevator_mines_end":{"category":"music","sounds":["doors/elevator_mines_end"]},
    "doors.mines_intro":{"category":"music","sounds":["doors/mines_intro"]},

    "doors.seek_mines_intro":{"category":"music","sounds":["doors/seek_mines_intro"]},
    "doors.seek_mines_loop_chill":{"category":"music","sounds":["doors/seek_mines_loop_chill"]},
    "doors.seek_mines_cutscene":{"category":"music","sounds":["doors/seek_mines_cutscene"]},
    "doors.seek_mines_loop_hype":{"category":"music","sounds":["doors/seek_mines_loop_hype"]},
    "doors.seek_mines_loop_minecart_chill":{"category":"music","sounds":["doors/seek_mines_loop_minecart_chill"]},
    "doors.seek_mines_ending":{"category":"music","sounds":["doors/seek_mines_ending"]},
    "doors.seek_mines_ending_grumble":{"category":"music","sounds":["doors/seek_mines_ending_grumble"]},

    "doors.grumble_phase_1":{"category":"music","sounds":["doors/grumble_phase_1"]},
    "doors.grumble_phase_2":{"category":"music","sounds":["doors/grumble_phase_2"]},
    "doors.grumble_phase_3":{"category":"music","sounds":["doors/grumble_phase_3"]},
    "doors.grumble_phase_4":{"category":"music","sounds":["doors/grumble_phase_4"]},
    "doors.grumble_intense":{"category":"music","sounds":["doors/grumble_intense"]},
    "doors.grumble_ending":{"category":"music","sounds":["doors/grumble_ending"]},

    "doors.jeffs_jam":{"category":"music","sounds":["doors/jeffs_jam"]},

    "doors.seek_sewer_start":{"category":"music","sounds":["doors/seek_sewer_start"]},
    "doors.seek_sewer_phase_1":{"category":"music","sounds":["doors/seek_sewer_phase_1"]},
    "doors.seek_sewer_phase_2":{"category":"music","sounds":["doors/seek_sewer_phase_2"]},
    "doors.seek_sewer_phase_3":{"category":"music","sounds":["doors/seek_sewer_phase_3"]},
    "doors.seek_sewer_end":{"category":"music","sounds":["doors/seek_sewer_end"]},

    "doors.fresh_rain_loop":{"category":"music","sounds":["doors/fresh_rain_loop"]},
    "doors.ending_outside_cutscene":{"category":"music","sounds":["doors/ending_outside_cutscene"]},

    "doors.sfx.elevator.bell":{"category":"master","sounds":["doors/sfx/elevator/bell"]},
    "doors.sfx.elevator.door_move":{"category":"master","sounds":["doors/sfx/elevator/door_move"]},
    "doors.sfx.elevator.major_timer_tick":{"category":"master","sounds":["doors/sfx/elevator/major_timer_tick"]},
    "doors.sfx.elevator.player_enter":{"category":"master","sounds":["doors/sfx/elevator/player_enter"]},
    "doors.sfx.elevator.timer_tick":{"category":"master","sounds":["doors/sfx/elevator/timer_tick"]},

    "doors.sfx.breaker.beep_off":{"sounds":["doors/sfx/breaker/beep_off"]},
    "doors.sfx.breaker.beep_on":{"sounds":["doors/sfx/breaker/beep_on"]},
    "doors.sfx.breaker.correct":{"sounds":["doors/sfx/breaker/correct"]},
    "doors.sfx.breaker.progress":{"sounds":["doors/sfx/breaker/progress"]},

    "doors.sfx.entities.rush_far1":{"sounds":["doors/sfx/entities/rush_far1"]},
    "doors.sfx.entities.rush_far2":{"sounds":["doors/sfx/entities/rush_far2"]},
    "doors.sfx.entities.rush_far3":{"sounds":["doors/sfx/entities/rush_far3"]},
    "doors.sfx.entities.rush_far4":{"sounds":["doors/sfx/entities/rush_far4"]},
    "doors.sfx.entities.rush_far5":{"sounds":["doors/sfx/entities/rush_far5"]},
    "doors.sfx.entities.rush_far6":{"sounds":["doors/sfx/entities/rush_far6"]},
    "doors.sfx.entities.rush_far7":{"sounds":["doors/sfx/entities/rush_far7"]},
    "doors.sfx.entities.rush_far8":{"sounds":["doors/sfx/entities/rush_far8"]},
    "doors.sfx.entities.rush_far9":{"sounds":["doors/sfx/entities/rush_far9"]},
    "doors.sfx.entities.rush_far10":{"sounds":["doors/sfx/entities/rush_far10"]},
    "doors.sfx.entities.rush_far11":{"sounds":["doors/sfx/entities/rush_far11"]},
    "doors.sfx.entities.rush_far12":{"sounds":["doors/sfx/entities/rush_far12"]},
    "doors.sfx.entities.rush_far13":{"sounds":["doors/sfx/entities/rush_far13"]},
    "doors.sfx.entities.rush_far14":{"sounds":["doors/sfx/entities/rush_far14"]},
    "doors.sfx.entities.rush_far15":{"sounds":["doors/sfx/entities/rush_far15"]},
    "doors.sfx.entities.rush_far16":{"sounds":["doors/sfx/entities/rush_far16"]},
    "doors.sfx.entities.rush_far17":{"sounds":["doors/sfx/entities/rush_far17"]},
    "doors.sfx.entities.rush_far18":{"sounds":["doors/sfx/entities/rush_far18"]},
    "doors.sfx.entities.rush_far19":{"sounds":["doors/sfx/entities/rush_far19"]},
    "doors.sfx.entities.rush_far20":{"sounds":["doors/sfx/entities/rush_far20"]},
    "doors.sfx.entities.rush_far21":{"sounds":["doors/sfx/entities/rush_far21"]},
    "doors.sfx.entities.rush_far22":{"sounds":["doors/sfx/entities/rush_far22"]},
    "doors.sfx.entities.rush_far23":{"sounds":["doors/sfx/entities/rush_far23"]},
    "doors.sfx.entities.rush_far24":{"sounds":["doors/sfx/entities/rush_far24"]},
    "doors.sfx.entities.rush_far25":{"sounds":["doors/sfx/entities/rush_far25"]},
    "doors.sfx.entities.rush_far26":{"sounds":["doors/sfx/entities/rush_far26"]},
    "doors.sfx.entities.rush_far27":{"sounds":["doors/sfx/entities/rush_far27"]},
    "doors.sfx.entities.rush_far28":{"sounds":["doors/sfx/entities/rush_far28"]},
    "doors.sfx.entities.rush_far29":{"sounds":["doors/sfx/entities/rush_far29"]},
    "doors.sfx.entities.rush_far30":{"sounds":["doors/sfx/entities/rush_far30"]},
    "doors.sfx.entities.rush_far31":{"sounds":["doors/sfx/entities/rush_far31"]},
    "doors.sfx.entities.rush_far32":{"sounds":["doors/sfx/entities/rush_far32"]},
    "doors.sfx.entities.rush_far33":{"sounds":["doors/sfx/entities/rush_far33"]},
    "doors.sfx.entities.rush_far34":{"sounds":["doors/sfx/entities/rush_far34"]},
    "doors.sfx.entities.rush_far35":{"sounds":["doors/sfx/entities/rush_far35"]},
    "doors.sfx.entities.rush_far36":{"sounds":["doors/sfx/entities/rush_far36"]},
    "doors.sfx.entities.rush_far37":{"sounds":["doors/sfx/entities/rush_far37"]},
    "doors.sfx.entities.rush_far38":{"sounds":["doors/sfx/entities/rush_far38"]},
    "doors.sfx.entities.rush_far39":{"sounds":["doors/sfx/entities/rush_far39"]},
    "doors.sfx.entities.rush_far40":{"sounds":["doors/sfx/entities/rush_far40"]},
    "doors.sfx.entities.rush_far41":{"sounds":["doors/sfx/entities/rush_far41"]},

    "doors.sfx.entities.rush_near1":{"sounds":["doors/sfx/entities/rush_near1"]},
    "doors.sfx.entities.rush_near2":{"sounds":["doors/sfx/entities/rush_near2"]},
    "doors.sfx.entities.rush_near3":{"sounds":["doors/sfx/entities/rush_near3"]},
    "doors.sfx.entities.rush_near4":{"sounds":["doors/sfx/entities/rush_near4"]},
    "doors.sfx.entities.rush_near5":{"sounds":["doors/sfx/entities/rush_near5"]},
    "doors.sfx.entities.rush_near6":{"sounds":["doors/sfx/entities/rush_near6"]},
    "doors.sfx.entities.rush_near7":{"sounds":["doors/sfx/entities/rush_near7"]},
    "doors.sfx.entities.rush_near8":{"sounds":["doors/sfx/entities/rush_near8"]},
    "doors.sfx.entities.rush_near9":{"sounds":["doors/sfx/entities/rush_near9"]},
    "doors.sfx.entities.rush_near10":{"sounds":["doors/sfx/entities/rush_near10"]},
    "doors.sfx.entities.rush_near11":{"sounds":["doors/sfx/entities/rush_near11"]},
    "doors.sfx.entities.rush_near12":{"sounds":["doors/sfx/entities/rush_near12"]},

    "doors.sfx.entities.rush_crucify":{"sounds":["doors/sfx/entities/rush_crucify"]},
    "doors.sfx.entities.rush_fakeout_1":{"category":"ambient","sounds":["doors/sfx/entities/rush_fakeout_1"]},
    "doors.sfx.entities.rush_fakeout_2":{"category":"ambient","sounds":["doors/sfx/entities/rush_fakeout_2"]},
    "doors.sfx.entities.rush_jumpscare":{"sounds":["doors/sfx/entities/rush_jumpscare"]},
    "doors.sfx.entities.rush_kill":{"category":"master","sounds":["doors/sfx/entities/rush_kill"]},
    "doors.sfx.entities.rush_static":{"sounds":["doors/sfx/entities/rush_static"]},

    "doors.sfx.entities.ambush_far1":{"sounds":["doors/sfx/entities/ambush_far1"]},
    "doors.sfx.entities.ambush_far2":{"sounds":["doors/sfx/entities/ambush_far2"]},
    "doors.sfx.entities.ambush_far3":{"sounds":["doors/sfx/entities/ambush_far3"]},
    "doors.sfx.entities.ambush_far4":{"sounds":["doors/sfx/entities/ambush_far4"]},
    "doors.sfx.entities.ambush_far5":{"sounds":["doors/sfx/entities/ambush_far5"]},
    "doors.sfx.entities.ambush_far6":{"sounds":["doors/sfx/entities/ambush_far6"]},
    "doors.sfx.entities.ambush_far7":{"sounds":["doors/sfx/entities/ambush_far7"]},
    "doors.sfx.entities.ambush_far8":{"sounds":["doors/sfx/entities/ambush_far8"]},

    "doors.sfx.entities.ambush_near1":{"sounds":["doors/sfx/entities/ambush_near1"]},
    "doors.sfx.entities.ambush_near2":{"sounds":["doors/sfx/entities/ambush_near2"]},
    "doors.sfx.entities.ambush_near3":{"sounds":["doors/sfx/entities/ambush_near3"]},
    "doors.sfx.entities.ambush_near4":{"sounds":["doors/sfx/entities/ambush_near4"]},
    "doors.sfx.entities.ambush_near5":{"sounds":["doors/sfx/entities/ambush_near5"]},
    "doors.sfx.entities.ambush_near6":{"sounds":["doors/sfx/entities/ambush_near6"]},
    "doors.sfx.entities.ambush_near7":{"sounds":["doors/sfx/entities/ambush_near7"]},

    "doors.sfx.entities.ambush_crucify":{"sounds":["doors/sfx/entities/ambush_crucify"]},
    "doors.sfx.entities.ambush_jumpscare_1":{"sounds":["doors/sfx/entities/ambush_jumpscare_1"]},
    "doors.sfx.entities.ambush_jumpscare_2":{"sounds":["doors/sfx/entities/ambush_jumpscare_2"]},

    "doors.sfx.entities.screech_psst":{"sounds":["doors/sfx/entities/screech_psst"]},
    "doors.sfx.entities.screech_caught":{"sounds":["doors/sfx/entities/screech_caught"]},
    "doors.sfx.entities.screech_crucify":{"sounds":["doors/sfx/entities/screech_crucify"]},
    "doors.sfx.entities.screech_bite":{"sounds":["doors/sfx/entities/screech_bite"]},
    "doors.sfx.entities.screech_caught_super_hard_mode":{"sounds":["doors/sfx/entities/screech_caught_super_hard_mode"]},
    "doors.sfx.entities.screech_explode":{"sounds":["doors/sfx/entities/screech_explode"]},

    "doors.sfx.entities.seek_eye_spawn":{"sounds":["doors/sfx/entities/seek_eye_spawn"]},
    "doors.sfx.entities.seek_eye_blink":{"sounds":["doors/sfx/entities/seek_eye_blink"]},
    "doors.sfx.entities.seek_far_ambience":{"category":"ambience","sounds":["doors/sfx/entities/seek_far_ambience"]},
    "doors.sfx.entities.seek_jumpscare":{"sounds":["doors/sfx/entities/seek_jumpscare"]},
    "doors.sfx.entities.seek_kill":{"sounds":["doors/sfx/entities/seek_kill"]},
    "doors.sfx.entities.seek_knock":{"sounds":["doors/sfx/entities/seek_knock"]},
    "doors.sfx.entities.seek_scream":{"sounds":["doors/sfx/entities/seek_scream"]},
    "doors.sfx.entities.seek_footsteps_close1":{"sounds":["doors/sfx/entities/seek_footsteps_close1"]},
    "doors.sfx.entities.seek_footsteps_close2":{"sounds":["doors/sfx/entities/seek_footsteps_close2"]},
    "doors.sfx.entities.seek_footsteps_close3":{"sounds":["doors/sfx/entities/seek_footsteps_close3"]},
    "doors.sfx.entities.seek_footsteps_close4":{"sounds":["doors/sfx/entities/seek_footsteps_close4"]},
    "doors.sfx.entities.seek_footsteps_close5":{"sounds":["doors/sfx/entities/seek_footsteps_close5"]},
    "doors.sfx.entities.seek_footsteps_close6":{"sounds":["doors/sfx/entities/seek_footsteps_close6"]},
    "doors.sfx.entities.seek_footsteps_close7":{"sounds":["doors/sfx/entities/seek_footsteps_close7"]},
    "doors.sfx.entities.seek_footsteps_close8":{"sounds":["doors/sfx/entities/seek_footsteps_close8"]},
    "doors.sfx.entities.seek_footsteps_close9":{"sounds":["doors/sfx/entities/seek_footsteps_close9"]},
    "doors.sfx.entities.seek_footsteps_close10":{"sounds":["doors/sfx/entities/seek_footsteps_close10"]},
    "doors.sfx.entities.seek_footsteps_close11":{"sounds":["doors/sfx/entities/seek_footsteps_close11"]},
    "doors.sfx.entities.seek_footsteps_close12":{"sounds":["doors/sfx/entities/seek_footsteps_close12"]},
    "doors.sfx.entities.seek_footsteps_close13":{"sounds":["doors/sfx/entities/seek_footsteps_close13"]},

    "doors.sfx.entities.seek_footsteps_far1":{"sounds":["doors/sfx/entities/seek_footsteps_far1"]},
    "doors.sfx.entities.seek_footsteps_far2":{"sounds":["doors/sfx/entities/seek_footsteps_far2"]},
    "doors.sfx.entities.seek_footsteps_far3":{"sounds":["doors/sfx/entities/seek_footsteps_far3"]},
    "doors.sfx.entities.seek_footsteps_far4":{"sounds":["doors/sfx/entities/seek_footsteps_far4"]},
    "doors.sfx.entities.seek_footsteps_far5":{"sounds":["doors/sfx/entities/seek_footsteps_far5"]},
    "doors.sfx.entities.seek_footsteps_far6":{"sounds":["doors/sfx/entities/seek_footsteps_far6"]},
    "doors.sfx.entities.seek_footsteps_far7":{"sounds":["doors/sfx/entities/seek_footsteps_far7"]},
    "doors.sfx.entities.seek_footsteps_far8":{"sounds":["doors/sfx/entities/seek_footsteps_far8"]},
    "doors.sfx.entities.seek_footsteps_far9":{"sounds":["doors/sfx/entities/seek_footsteps_far9"]},
    "doors.sfx.entities.seek_footsteps_far10":{"sounds":["doors/sfx/entities/seek_footsteps_far10"]},
    "doors.sfx.entities.seek_footsteps_far11":{"sounds":["doors/sfx/entities/seek_footsteps_far11"]},
    "doors.sfx.entities.seek_footsteps_far12":{"sounds":["doors/sfx/entities/seek_footsteps_far12"]},
    "doors.sfx.entities.seek_footsteps_far13":{"sounds":["doors/sfx/entities/seek_footsteps_far13"]},
    
    "doors.sfx.entities.figure_eat":{"sounds":["doors/sfx/entities/figure_eat"]},
    "doors.sfx.entities.figure_kill":{"sounds":["doors/sfx/entities/figure_kill"]},
    "doors.sfx.entities.figure_growl_low":{"sounds":["doors/sfx/entities/figure_growl_low"]},
    "doors.sfx.entities.figure_growl_high":{"sounds":["doors/sfx/entities/figure_growl_high"]},
    "doors.sfx.entities.figure_growl_agro":{"sounds":["doors/sfx/entities/figure_growl_agro"]},
    "doors.sfx.entities.figure_grunt_low":{"sounds":["doors/sfx/entities/figure_grunt_low"]},
    "doors.sfx.entities.figure_grunt_high":{"sounds":["doors/sfx/entities/figure_grunt_high"]},
    "doors.sfx.entities.figure_footstep_1":{"sounds":["doors/sfx/entities/figure_footstep_1"]},
    "doors.sfx.entities.figure_footstep_2":{"sounds":["doors/sfx/entities/figure_footstep_2"]},
    "doors.sfx.entities.figure_door_pound":{"sounds":["doors/sfx/entities/figure_door_pound"]},
    "doors.sfx.entities.figure_door_break":{"sounds":["doors/sfx/entities/figure_door_break"]},
    "doors.sfx.entities.figure_elevator_door_pound":{"sounds":["doors/sfx/entities/figure_elevator_door_pound"]},
    "doors.sfx.entities.figure_death_super_hard_mode":{"sounds":["doors/sfx/entities/figure_death_super_hard_mode"]},

    "doors.sfx.entities.haste_jumpscare":{"sounds":["doors/sfx/entities/haste_jumpscare"]},

    "doors.sfx.entities.halt_whisper_enter":{"sounds":["doors/sfx/entities/halt_whisper_enter"]},
    "doors.sfx.entities.halt_whisper":{"sounds":["doors/sfx/entities/halt_whisper"]},
    "doors.sfx.entities.halt_whisper_weird":{"sounds":["doors/sfx/entities/halt_whisper_weird"]},
    "doors.sfx.entities.halt_jumpscare":{"sounds":["doors/sfx/entities/halt_jumpscare"]},
    "doors.sfx.entities.halt_turn":{"sounds":["doors/sfx/entities/halt_turn"]},
    "doors.sfx.entities.halt_crucify":{"sounds":["doors/sfx/entities/halt_crucify"]},

    "doors.sfx.entities.eyes_spawn":{"sounds":["doors/sfx/entities/eyes_spawn"]},
    "doors.sfx.entities.eyes_ambience":{"sounds":["doors/sfx/entities/eyes_ambience"]},
    "doors.sfx.entities.eyes_teleport":{"sounds":["doors/sfx/entities/eyes_teleport"]},
    "doors.sfx.entities.eyes_attack":{"sounds":["doors/sfx/entities/eyes_attack"]},
    "doors.sfx.entities.eyes_repent":{"sounds":["doors/sfx/entities/eyes_repent"]},
    "doors.sfx.entities.eyes_crucify":{"sounds":["doors/sfx/entities/eyes_crucify"]},

    "doors.sfx.entities.snare_trap":{"sounds":["doors/sfx/entities/snare_trap"]},

    "doors.sfx.entities.dupe_growl":{"sounds":["doors/sfx/entities/dupe_growl"]},
    "doors.sfx.entities.dupe_jumpscare":{"sounds":["doors/sfx/entities/dupe_jumpscare"]},
    "doors.sfx.entities.dupe_crucify":{"sounds":["doors/sfx/entities/dupe_crucify"]},

    "doors.sfx.entities.hide_whispers":{"sounds":["doors/sfx/entities/hide_whispers"]},
    "doors.sfx.entities.hide_jumpscare":{"sounds":["doors/sfx/entities/hide_jumpscare"]},
    "doors.sfx.entities.hide_static":{"sounds":["doors/sfx/entities/hide_static"]},
    "doors.sfx.entities.hide_whispers_mines":{"sounds":["doors/sfx/entities/hide_whispers_mines"]},

    "doors.sfx.entities.jack_jumpscare":{"sounds":["doors/sfx/entities/jack_jumpscare"]},

    "doors.sfx.entities.shadow_jumpscare":{"sounds":["doors/sfx/entities/shadow_jumpscare"]},

    "doors.sfx.entities.timothy_hiss":{"sounds":["doors/sfx/entities/timothy_hiss"]},
    "doors.sfx.entities.timothy_jumpscare":{"sounds":["doors/sfx/entities/timothy_jumpscare"]},

    "doors.sfx.entities.a-60_rumble1":{"sounds":["doors/sfx/entities/a-60_rumble1"]},
    "doors.sfx.entities.a-60_rumble2":{"sounds":["doors/sfx/entities/a-60_rumble2"]},
    "doors.sfx.entities.a-60_rumble3":{"sounds":["doors/sfx/entities/a-60_rumble3"]},
    "doors.sfx.entities.a-60_rumble4":{"sounds":["doors/sfx/entities/a-60_rumble4"]},
    "doors.sfx.entities.a-60_rumble5":{"sounds":["doors/sfx/entities/a-60_rumble5"]},
    "doors.sfx.entities.a-60_rumble6":{"sounds":["doors/sfx/entities/a-60_rumble6"]},
    "doors.sfx.entities.a-60_rumble7":{"sounds":["doors/sfx/entities/a-60_rumble7"]},
    "doors.sfx.entities.a-60_rumble8":{"sounds":["doors/sfx/entities/a-60_rumble8"]},
    "doors.sfx.entities.a-60_rumble9":{"sounds":["doors/sfx/entities/a-60_rumble9"]},
    "doors.sfx.entities.a-60_rumble10":{"sounds":["doors/sfx/entities/a-60_rumble10"]},
    "doors.sfx.entities.a-60_rumble11":{"sounds":["doors/sfx/entities/a-60_rumble11"]},
    "doors.sfx.entities.a-60_rumble12":{"sounds":["doors/sfx/entities/a-60_rumble12"]},
    "doors.sfx.entities.a-60_rumble13":{"sounds":["doors/sfx/entities/a-60_rumble13"]},
    "doors.sfx.entities.a-60_rumble14":{"sounds":["doors/sfx/entities/a-60_rumble14"]},
    "doors.sfx.entities.a-60_rumble15":{"sounds":["doors/sfx/entities/a-60_rumble15"]},
    "doors.sfx.entities.a-60_rumble16":{"sounds":["doors/sfx/entities/a-60_rumble16"]},
    "doors.sfx.entities.a-60_rumble17":{"sounds":["doors/sfx/entities/a-60_rumble17"]},
    "doors.sfx.entities.a-60_rumble18":{"sounds":["doors/sfx/entities/a-60_rumble18"]},
    "doors.sfx.entities.a-60_rumble19":{"sounds":["doors/sfx/entities/a-60_rumble19"]},
    "doors.sfx.entities.a-60_rumble20":{"sounds":["doors/sfx/entities/a-60_rumble20"]},
    "doors.sfx.entities.a-60_rumble21":{"sounds":["doors/sfx/entities/a-60_rumble21"]},
    "doors.sfx.entities.a-60_rumble22":{"sounds":["doors/sfx/entities/a-60_rumble22"]},
    "doors.sfx.entities.a-60_rumble23":{"sounds":["doors/sfx/entities/a-60_rumble23"]},
    "doors.sfx.entities.a-60_rumble24":{"sounds":["doors/sfx/entities/a-60_rumble24"]},

    "doors.sfx.entities.a-60_distant1":{"sounds":["doors/sfx/entities/a-60_distant1"]},
    "doors.sfx.entities.a-60_distant2":{"sounds":["doors/sfx/entities/a-60_distant2"]},
    "doors.sfx.entities.a-60_distant3":{"sounds":["doors/sfx/entities/a-60_distant3"]},
    "doors.sfx.entities.a-60_distant4":{"sounds":["doors/sfx/entities/a-60_distant4"]},
    "doors.sfx.entities.a-60_distant5":{"sounds":["doors/sfx/entities/a-60_distant5"]},
    "doors.sfx.entities.a-60_distant6":{"sounds":["doors/sfx/entities/a-60_distant6"]},
    "doors.sfx.entities.a-60_distant7":{"sounds":["doors/sfx/entities/a-60_distant7"]},
    "doors.sfx.entities.a-60_distant8":{"sounds":["doors/sfx/entities/a-60_distant8"]},
    "doors.sfx.entities.a-60_distant9":{"sounds":["doors/sfx/entities/a-60_distant9"]},
    "doors.sfx.entities.a-60_distant10":{"sounds":["doors/sfx/entities/a-60_distant10"]},
    "doors.sfx.entities.a-60_distant11":{"sounds":["doors/sfx/entities/a-60_distant11"]},
    "doors.sfx.entities.a-60_distant12":{"sounds":["doors/sfx/entities/a-60_distant12"]},
    "doors.sfx.entities.a-60_distant13":{"sounds":["doors/sfx/entities/a-60_distant13"]},
    "doors.sfx.entities.a-60_distant14":{"sounds":["doors/sfx/entities/a-60_distant14"]},
    "doors.sfx.entities.a-60_distant15":{"sounds":["doors/sfx/entities/a-60_distant15"]},
    "doors.sfx.entities.a-60_distant16":{"sounds":["doors/sfx/entities/a-60_distant16"]},
    "doors.sfx.entities.a-60_distant17":{"sounds":["doors/sfx/entities/a-60_distant17"]},
    "doors.sfx.entities.a-60_distant18":{"sounds":["doors/sfx/entities/a-60_distant18"]},
    "doors.sfx.entities.a-60_distant19":{"sounds":["doors/sfx/entities/a-60_distant19"]},
    "doors.sfx.entities.a-60_distant20":{"sounds":["doors/sfx/entities/a-60_distant20"]},
    "doors.sfx.entities.a-60_distant21":{"sounds":["doors/sfx/entities/a-60_distant21"]},
    "doors.sfx.entities.a-60_distant22":{"sounds":["doors/sfx/entities/a-60_distant22"]},
    "doors.sfx.entities.a-60_distant23":{"sounds":["doors/sfx/entities/a-60_distant23"]},
    "doors.sfx.entities.a-60_distant24":{"sounds":["doors/sfx/entities/a-60_distant24"]},
    "doors.sfx.entities.a-60_distant25":{"sounds":["doors/sfx/entities/a-60_distant25"]},
    "doors.sfx.entities.a-60_distant26":{"sounds":["doors/sfx/entities/a-60_distant26"]},
    "doors.sfx.entities.a-60_distant27":{"sounds":["doors/sfx/entities/a-60_distant27"]},
    "doors.sfx.entities.a-60_distant28":{"sounds":["doors/sfx/entities/a-60_distant28"]},
    "doors.sfx.entities.a-60_distant29":{"sounds":["doors/sfx/entities/a-60_distant29"]},
    "doors.sfx.entities.a-60_distant30":{"sounds":["doors/sfx/entities/a-60_distant30"]},
    "doors.sfx.entities.a-60_distant31":{"sounds":["doors/sfx/entities/a-60_distant31"]},
    "doors.sfx.entities.a-60_distant32":{"sounds":["doors/sfx/entities/a-60_distant32"]},
    "doors.sfx.entities.a-60_distant33":{"sounds":["doors/sfx/entities/a-60_distant33"]},
    "doors.sfx.entities.a-60_distant34":{"sounds":["doors/sfx/entities/a-60_distant34"]},
    "doors.sfx.entities.a-60_distant35":{"sounds":["doors/sfx/entities/a-60_distant35"]},
    "doors.sfx.entities.a-60_distant36":{"sounds":["doors/sfx/entities/a-60_distant36"]},
    "doors.sfx.entities.a-60_distant37":{"sounds":["doors/sfx/entities/a-60_distant37"]},
    "doors.sfx.entities.a-60_distant38":{"sounds":["doors/sfx/entities/a-60_distant38"]},
    "doors.sfx.entities.a-60_distant39":{"sounds":["doors/sfx/entities/a-60_distant39"]},
    "doors.sfx.entities.a-60_distant40":{"sounds":["doors/sfx/entities/a-60_distant40"]},
    "doors.sfx.entities.a-60_distant41":{"sounds":["doors/sfx/entities/a-60_distant41"]},
    "doors.sfx.entities.a-60_distant42":{"sounds":["doors/sfx/entities/a-60_distant42"]},
    "doors.sfx.entities.a-60_distant43":{"sounds":["doors/sfx/entities/a-60_distant43"]},
    "doors.sfx.entities.a-60_distant44":{"sounds":["doors/sfx/entities/a-60_distant44"]},
    "doors.sfx.entities.a-60_distant45":{"sounds":["doors/sfx/entities/a-60_distant45"]},
    "doors.sfx.entities.a-60_distant46":{"sounds":["doors/sfx/entities/a-60_distant46"]},
    "doors.sfx.entities.a-60_distant47":{"sounds":["doors/sfx/entities/a-60_distant47"]},
    "doors.sfx.entities.a-60_distant48":{"sounds":["doors/sfx/entities/a-60_distant48"]},
    "doors.sfx.entities.a-60_distant49":{"sounds":["doors/sfx/entities/a-60_distant49"]},
    "doors.sfx.entities.a-60_distant50":{"sounds":["doors/sfx/entities/a-60_distant50"]},
    "doors.sfx.entities.a-60_distant51":{"sounds":["doors/sfx/entities/a-60_distant51"]},
    "doors.sfx.entities.a-60_distant52":{"sounds":["doors/sfx/entities/a-60_distant52"]},
    "doors.sfx.entities.a-60_distant53":{"sounds":["doors/sfx/entities/a-60_distant53"]},
    "doors.sfx.entities.a-60_distant54":{"sounds":["doors/sfx/entities/a-60_distant54"]},
    "doors.sfx.entities.a-60_distant55":{"sounds":["doors/sfx/entities/a-60_distant55"]},
    "doors.sfx.entities.a-60_distant56":{"sounds":["doors/sfx/entities/a-60_distant56"]},
    "doors.sfx.entities.a-60_distant57":{"sounds":["doors/sfx/entities/a-60_distant57"]},
    "doors.sfx.entities.a-60_distant58":{"sounds":["doors/sfx/entities/a-60_distant58"]},
    "doors.sfx.entities.a-60_distant59":{"sounds":["doors/sfx/entities/a-60_distant59"]},
    "doors.sfx.entities.a-60_distant60":{"sounds":["doors/sfx/entities/a-60_distant60"]},
    "doors.sfx.entities.a-60_distant61":{"sounds":["doors/sfx/entities/a-60_distant61"]},
    "doors.sfx.entities.a-60_distant62":{"sounds":["doors/sfx/entities/a-60_distant62"]},
    "doors.sfx.entities.a-60_distant63":{"sounds":["doors/sfx/entities/a-60_distant63"]},
    "doors.sfx.entities.a-60_distant64":{"sounds":["doors/sfx/entities/a-60_distant64"]},
    "doors.sfx.entities.a-60_distant65":{"sounds":["doors/sfx/entities/a-60_distant65"]},
    "doors.sfx.entities.a-60_distant66":{"sounds":["doors/sfx/entities/a-60_distant66"]},
    "doors.sfx.entities.a-60_distant67":{"sounds":["doors/sfx/entities/a-60_distant67"]},

    "doors.sfx.entities.a-60_fakeout":{"sounds":["doors/sfx/entities/a-60_fakeout"]},

    "doors.sfx.entities.a-60_near1":{"sounds":["doors/sfx/entities/a-60_near1"]},
    "doors.sfx.entities.a-60_near2":{"sounds":["doors/sfx/entities/a-60_near2"]},
    "doors.sfx.entities.a-60_near3":{"sounds":["doors/sfx/entities/a-60_near3"]},
    "doors.sfx.entities.a-60_near4":{"sounds":["doors/sfx/entities/a-60_near4"]},
    "doors.sfx.entities.a-60_near5":{"sounds":["doors/sfx/entities/a-60_near5"]},
    "doors.sfx.entities.a-60_near6":{"sounds":["doors/sfx/entities/a-60_near6"]},
    "doors.sfx.entities.a-60_near7":{"sounds":["doors/sfx/entities/a-60_near7"]},
    "doors.sfx.entities.a-60_near8":{"sounds":["doors/sfx/entities/a-60_near8"]},

    "doors.sfx.entities.a-90_spawn":{"sounds":["doors/sfx/entities/a-90_spawn"]},
    "doors.sfx.entities.a-90_jumpscare":{"sounds":["doors/sfx/entities/a-90_jumpscare"]},
    "doors.sfx.entities.a-90_fakeout":{"sounds":["doors/sfx/entities/a-90_fakeout"]},
    "doors.sfx.entities.a-90_crucify":{"sounds":["doors/sfx/entities/a-90_crucify"]},

    "doors.sfx.entities.a-120_distant1":{"sounds":["doors/sfx/entities/a-120_distant1"]},
    "doors.sfx.entities.a-120_distant2":{"sounds":["doors/sfx/entities/a-120_distant2"]},
    "doors.sfx.entities.a-120_distant3":{"sounds":["doors/sfx/entities/a-120_distant3"]},
    "doors.sfx.entities.a-120_distant4":{"sounds":["doors/sfx/entities/a-120_distant4"]},
    "doors.sfx.entities.a-120_distant5":{"sounds":["doors/sfx/entities/a-120_distant5"]},
    "doors.sfx.entities.a-120_distant6":{"sounds":["doors/sfx/entities/a-120_distant6"]},
    "doors.sfx.entities.a-120_distant7":{"sounds":["doors/sfx/entities/a-120_distant7"]},
    "doors.sfx.entities.a-120_distant8":{"sounds":["doors/sfx/entities/a-120_distant8"]},
    "doors.sfx.entities.a-120_distant9":{"sounds":["doors/sfx/entities/a-120_distant9"]},
    "doors.sfx.entities.a-120_distant10":{"sounds":["doors/sfx/entities/a-120_distant10"]},
    "doors.sfx.entities.a-120_distant11":{"sounds":["doors/sfx/entities/a-120_distant11"]},
    "doors.sfx.entities.a-120_distant12":{"sounds":["doors/sfx/entities/a-120_distant12"]},
    "doors.sfx.entities.a-120_distant13":{"sounds":["doors/sfx/entities/a-120_distant13"]},
    "doors.sfx.entities.a-120_distant14":{"sounds":["doors/sfx/entities/a-120_distant14"]},
    "doors.sfx.entities.a-120_distant15":{"sounds":["doors/sfx/entities/a-120_distant15"]},
    "doors.sfx.entities.a-120_distant16":{"sounds":["doors/sfx/entities/a-120_distant16"]},
    "doors.sfx.entities.a-120_distant17":{"sounds":["doors/sfx/entities/a-120_distant17"]},
    "doors.sfx.entities.a-120_distant18":{"sounds":["doors/sfx/entities/a-120_distant18"]},
    "doors.sfx.entities.a-120_distant19":{"sounds":["doors/sfx/entities/a-120_distant19"]},
    "doors.sfx.entities.a-120_distant20":{"sounds":["doors/sfx/entities/a-120_distant20"]},
    "doors.sfx.entities.a-120_distant21":{"sounds":["doors/sfx/entities/a-120_distant21"]},
    "doors.sfx.entities.a-120_distant22":{"sounds":["doors/sfx/entities/a-120_distant22"]},
    "doors.sfx.entities.a-120_distant23":{"sounds":["doors/sfx/entities/a-120_distant23"]},
    "doors.sfx.entities.a-120_distant24":{"sounds":["doors/sfx/entities/a-120_distant24"]},
    "doors.sfx.entities.a-120_distant25":{"sounds":["doors/sfx/entities/a-120_distant25"]},
    "doors.sfx.entities.a-120_distant26":{"sounds":["doors/sfx/entities/a-120_distant26"]},
    "doors.sfx.entities.a-120_distant27":{"sounds":["doors/sfx/entities/a-120_distant27"]},
    "doors.sfx.entities.a-120_distant28":{"sounds":["doors/sfx/entities/a-120_distant28"]},
    "doors.sfx.entities.a-120_distant29":{"sounds":["doors/sfx/entities/a-120_distant29"]},
    "doors.sfx.entities.a-120_distant30":{"sounds":["doors/sfx/entities/a-120_distant30"]},
    "doors.sfx.entities.a-120_distant31":{"sounds":["doors/sfx/entities/a-120_distant31"]},
    "doors.sfx.entities.a-120_distant32":{"sounds":["doors/sfx/entities/a-120_distant32"]},
    "doors.sfx.entities.a-120_distant33":{"sounds":["doors/sfx/entities/a-120_distant33"]},
    "doors.sfx.entities.a-120_distant34":{"sounds":["doors/sfx/entities/a-120_distant34"]},
    "doors.sfx.entities.a-120_distant35":{"sounds":["doors/sfx/entities/a-120_distant35"]},
    "doors.sfx.entities.a-120_distant36":{"sounds":["doors/sfx/entities/a-120_distant36"]},
    "doors.sfx.entities.a-120_distant37":{"sounds":["doors/sfx/entities/a-120_distant37"]},
    "doors.sfx.entities.a-120_distant38":{"sounds":["doors/sfx/entities/a-120_distant38"]},
    "doors.sfx.entities.a-120_distant39":{"sounds":["doors/sfx/entities/a-120_distant39"]},
    "doors.sfx.entities.a-120_distant40":{"sounds":["doors/sfx/entities/a-120_distant40"]},
    "doors.sfx.entities.a-120_distant41":{"sounds":["doors/sfx/entities/a-120_distant41"]},
    "doors.sfx.entities.a-120_distant42":{"sounds":["doors/sfx/entities/a-120_distant42"]},
    "doors.sfx.entities.a-120_distant43":{"sounds":["doors/sfx/entities/a-120_distant43"]},
    "doors.sfx.entities.a-120_distant44":{"sounds":["doors/sfx/entities/a-120_distant44"]},
    "doors.sfx.entities.a-120_distant45":{"sounds":["doors/sfx/entities/a-120_distant45"]},
    "doors.sfx.entities.a-120_distant46":{"sounds":["doors/sfx/entities/a-120_distant46"]},
    "doors.sfx.entities.a-120_distant47":{"sounds":["doors/sfx/entities/a-120_distant47"]},
    "doors.sfx.entities.a-120_distant48":{"sounds":["doors/sfx/entities/a-120_distant48"]},
    "doors.sfx.entities.a-120_distant49":{"sounds":["doors/sfx/entities/a-120_distant49"]},
    "doors.sfx.entities.a-120_distant50":{"sounds":["doors/sfx/entities/a-120_distant50"]},
    "doors.sfx.entities.a-120_distant51":{"sounds":["doors/sfx/entities/a-120_distant51"]},
    "doors.sfx.entities.a-120_distant52":{"sounds":["doors/sfx/entities/a-120_distant52"]},
    "doors.sfx.entities.a-120_distant53":{"sounds":["doors/sfx/entities/a-120_distant53"]},
    "doors.sfx.entities.a-120_distant54":{"sounds":["doors/sfx/entities/a-120_distant54"]},
    "doors.sfx.entities.a-120_distant55":{"sounds":["doors/sfx/entities/a-120_distant55"]},
    "doors.sfx.entities.a-120_distant56":{"sounds":["doors/sfx/entities/a-120_distant56"]},
    "doors.sfx.entities.a-120_distant57":{"sounds":["doors/sfx/entities/a-120_distant57"]},
    "doors.sfx.entities.a-120_distant58":{"sounds":["doors/sfx/entities/a-120_distant58"]},
    "doors.sfx.entities.a-120_distant59":{"sounds":["doors/sfx/entities/a-120_distant59"]},
    "doors.sfx.entities.a-120_distant60":{"sounds":["doors/sfx/entities/a-120_distant60"]},
    "doors.sfx.entities.a-120_distant61":{"sounds":["doors/sfx/entities/a-120_distant61"]},
    "doors.sfx.entities.a-120_distant62":{"sounds":["doors/sfx/entities/a-120_distant62"]},
    "doors.sfx.entities.a-120_distant63":{"sounds":["doors/sfx/entities/a-120_distant63"]},
    "doors.sfx.entities.a-120_distant64":{"sounds":["doors/sfx/entities/a-120_distant64"]},
    "doors.sfx.entities.a-120_distant65":{"sounds":["doors/sfx/entities/a-120_distant65"]},
    "doors.sfx.entities.a-120_distant66":{"sounds":["doors/sfx/entities/a-120_distant66"]},
    "doors.sfx.entities.a-120_distant67":{"sounds":["doors/sfx/entities/a-120_distant67"]},
    "doors.sfx.entities.a-120_distant68":{"sounds":["doors/sfx/entities/a-120_distant68"]},
    "doors.sfx.entities.a-120_distant69":{"sounds":["doors/sfx/entities/a-120_distant69"]},
    "doors.sfx.entities.a-120_distant70":{"sounds":["doors/sfx/entities/a-120_distant70"]},
    "doors.sfx.entities.a-120_distant71":{"sounds":["doors/sfx/entities/a-120_distant71"]},
    "doors.sfx.entities.a-120_distant72":{"sounds":["doors/sfx/entities/a-120_distant72"]},
    "doors.sfx.entities.a-120_distant73":{"sounds":["doors/sfx/entities/a-120_distant73"]},
    
    "doors.sfx.entities.a-120_near1":{"sounds":["doors/sfx/entities/a-120_near1"]},
    "doors.sfx.entities.a-120_near2":{"sounds":["doors/sfx/entities/a-120_near2"]},
    "doors.sfx.entities.a-120_near3":{"sounds":["doors/sfx/entities/a-120_near3"]},
    "doors.sfx.entities.a-120_near4":{"sounds":["doors/sfx/entities/a-120_near4"]},
    "doors.sfx.entities.a-120_near5":{"sounds":["doors/sfx/entities/a-120_near5"]},
    "doors.sfx.entities.a-120_near6":{"sounds":["doors/sfx/entities/a-120_near6"]},
    "doors.sfx.entities.a-120_near7":{"sounds":["doors/sfx/entities/a-120_near7"]},
    "doors.sfx.entities.a-120_near8":{"sounds":["doors/sfx/entities/a-120_near8"]},
    "doors.sfx.entities.a-120_near9":{"sounds":["doors/sfx/entities/a-120_near9"]},
    "doors.sfx.entities.a-120_near10":{"sounds":["doors/sfx/entities/a-120_near10"]},

    "doors.sfx.entities.a-120_kill":{"sounds":["doors/sfx/entities/a-120_kill"]},
    
    "doors.sfx.entities.grumble_kill":{"sounds":["doors/sfx/entities/grumble_kill"]},

    "doors.sfx.entities.grumble_laugh1":{"sounds":["doors/sfx/entities/grumble_laugh1"]},
    "doors.sfx.entities.grumble_laugh2":{"sounds":["doors/sfx/entities/grumble_laugh2"]},
    "doors.sfx.entities.grumble_laugh3":{"sounds":["doors/sfx/entities/grumble_laugh3"]},
    "doors.sfx.entities.grumble_laugh4":{"sounds":["doors/sfx/entities/grumble_laugh4"]},
    "doors.sfx.entities.grumble_laugh5":{"sounds":["doors/sfx/entities/grumble_laugh5"]},
    "doors.sfx.entities.grumble_laugh6":{"sounds":["doors/sfx/entities/grumble_laugh6"]},
    "doors.sfx.entities.grumble_laugh7":{"sounds":["doors/sfx/entities/grumble_laugh7"]},
    "doors.sfx.entities.grumble_laugh8":{"sounds":["doors/sfx/entities/grumble_laugh8"]},
    "doors.sfx.entities.grumble_laugh9":{"sounds":["doors/sfx/entities/grumble_laugh9"]},
    "doors.sfx.entities.grumble_laugh10":{"sounds":["doors/sfx/entities/grumble_laugh10"]},
    "doors.sfx.entities.grumble_laugh11":{"sounds":["doors/sfx/entities/grumble_laugh11"]},
    "doors.sfx.entities.grumble_laugh12":{"sounds":["doors/sfx/entities/grumble_laugh12"]},
    "doors.sfx.entities.grumble_laugh13":{"sounds":["doors/sfx/entities/grumble_laugh13"]},
    "doors.sfx.entities.grumble_laugh14":{"sounds":["doors/sfx/entities/grumble_laugh14"]},
    "doors.sfx.entities.grumble_laugh15":{"sounds":["doors/sfx/entities/grumble_laugh15"]},
    "doors.sfx.entities.grumble_laugh16":{"sounds":["doors/sfx/entities/grumble_laugh16"]},
    "doors.sfx.entities.grumble_laugh17":{"sounds":["doors/sfx/entities/grumble_laugh17"]},
    "doors.sfx.entities.grumble_laugh18":{"sounds":["doors/sfx/entities/grumble_laugh18"]},
    "doors.sfx.entities.grumble_laugh19":{"sounds":["doors/sfx/entities/grumble_laugh19"]},

    "doors.sfx.entities.grumble_move_high1":{"sounds":["doors/sfx/entities/grumble_move_high1"]},
    "doors.sfx.entities.grumble_move_high2":{"sounds":["doors/sfx/entities/grumble_move_high2"]},
    "doors.sfx.entities.grumble_move_high3":{"sounds":["doors/sfx/entities/grumble_move_high3"]},
    "doors.sfx.entities.grumble_move_high4":{"sounds":["doors/sfx/entities/grumble_move_high4"]},
    "doors.sfx.entities.grumble_move_high5":{"sounds":["doors/sfx/entities/grumble_move_high5"]},
    "doors.sfx.entities.grumble_move_high6":{"sounds":["doors/sfx/entities/grumble_move_high6"]},
    "doors.sfx.entities.grumble_move_high7":{"sounds":["doors/sfx/entities/grumble_move_high7"]},
    "doors.sfx.entities.grumble_move_high8":{"sounds":["doors/sfx/entities/grumble_move_high8"]},
    "doors.sfx.entities.grumble_move_high9":{"sounds":["doors/sfx/entities/grumble_move_high9"]},
    "doors.sfx.entities.grumble_move_high10":{"sounds":["doors/sfx/entities/grumble_move_high10"]},
    "doors.sfx.entities.grumble_move_high11":{"sounds":["doors/sfx/entities/grumble_move_high11"]},
    "doors.sfx.entities.grumble_move_high12":{"sounds":["doors/sfx/entities/grumble_move_high12"]},
    "doors.sfx.entities.grumble_move_high13":{"sounds":["doors/sfx/entities/grumble_move_high13"]},
    "doors.sfx.entities.grumble_move_high14":{"sounds":["doors/sfx/entities/grumble_move_high14"]},
    "doors.sfx.entities.grumble_move_high15":{"sounds":["doors/sfx/entities/grumble_move_high15"]},
    "doors.sfx.entities.grumble_move_high16":{"sounds":["doors/sfx/entities/grumble_move_high16"]},
    "doors.sfx.entities.grumble_move_high17":{"sounds":["doors/sfx/entities/grumble_move_high17"]},
    "doors.sfx.entities.grumble_move_high18":{"sounds":["doors/sfx/entities/grumble_move_high18"]},
    "doors.sfx.entities.grumble_move_high19":{"sounds":["doors/sfx/entities/grumble_move_high19"]},
    "doors.sfx.entities.grumble_move_high20":{"sounds":["doors/sfx/entities/grumble_move_high20"]},
    "doors.sfx.entities.grumble_move_high21":{"sounds":["doors/sfx/entities/grumble_move_high21"]},
    "doors.sfx.entities.grumble_move_high22":{"sounds":["doors/sfx/entities/grumble_move_high22"]},
    "doors.sfx.entities.grumble_move_high23":{"sounds":["doors/sfx/entities/grumble_move_high23"]},
    "doors.sfx.entities.grumble_move_high24":{"sounds":["doors/sfx/entities/grumble_move_high24"]},
    "doors.sfx.entities.grumble_move_high25":{"sounds":["doors/sfx/entities/grumble_move_high25"]},

    "doors.sfx.entities.grumble_move_low1":{"sounds":["doors/sfx/entities/grumble_move_low1"]},
    "doors.sfx.entities.grumble_move_low2":{"sounds":["doors/sfx/entities/grumble_move_low2"]},
    "doors.sfx.entities.grumble_move_low3":{"sounds":["doors/sfx/entities/grumble_move_low3"]},
    "doors.sfx.entities.grumble_move_low4":{"sounds":["doors/sfx/entities/grumble_move_low4"]},
    "doors.sfx.entities.grumble_move_low5":{"sounds":["doors/sfx/entities/grumble_move_low5"]},
    "doors.sfx.entities.grumble_move_low6":{"sounds":["doors/sfx/entities/grumble_move_low6"]},
    "doors.sfx.entities.grumble_move_low7":{"sounds":["doors/sfx/entities/grumble_move_low7"]},
    "doors.sfx.entities.grumble_move_low8":{"sounds":["doors/sfx/entities/grumble_move_low8"]},
    "doors.sfx.entities.grumble_move_low9":{"sounds":["doors/sfx/entities/grumble_move_low9"]},
    "doors.sfx.entities.grumble_move_low10":{"sounds":["doors/sfx/entities/grumble_move_low10"]},
    "doors.sfx.entities.grumble_move_low11":{"sounds":["doors/sfx/entities/grumble_move_low11"]},
    "doors.sfx.entities.grumble_move_low12":{"sounds":["doors/sfx/entities/grumble_move_low12"]},
    "doors.sfx.entities.grumble_move_low13":{"sounds":["doors/sfx/entities/grumble_move_low13"]},
    "doors.sfx.entities.grumble_move_low14":{"sounds":["doors/sfx/entities/grumble_move_low14"]},
    "doors.sfx.entities.grumble_move_low15":{"sounds":["doors/sfx/entities/grumble_move_low15"]},
    "doors.sfx.entities.grumble_move_low16":{"sounds":["doors/sfx/entities/grumble_move_low16"]},
    "doors.sfx.entities.grumble_move_low17":{"sounds":["doors/sfx/entities/grumble_move_low17"]},
    "doors.sfx.entities.grumble_move_low18":{"sounds":["doors/sfx/entities/grumble_move_low18"]},
    "doors.sfx.entities.grumble_move_low19":{"sounds":["doors/sfx/entities/grumble_move_low19"]},
    "doors.sfx.entities.grumble_move_low20":{"sounds":["doors/sfx/entities/grumble_move_low20"]},
    "doors.sfx.entities.grumble_move_low21":{"sounds":["doors/sfx/entities/grumble_move_low21"]},
    "doors.sfx.entities.grumble_move_low22":{"sounds":["doors/sfx/entities/grumble_move_low22"]},
    "doors.sfx.entities.grumble_move_low23":{"sounds":["doors/sfx/entities/grumble_move_low23"]},
    "doors.sfx.entities.grumble_move_low24":{"sounds":["doors/sfx/entities/grumble_move_low24"]},
    "doors.sfx.entities.grumble_move_low25":{"sounds":["doors/sfx/entities/grumble_move_low25"]},

    "doors.sfx.entities.grumble_roam1":{"sounds":["doors/sfx/entities/grumble_roam1"]},
    "doors.sfx.entities.grumble_roam2":{"sounds":["doors/sfx/entities/grumble_roam2"]},
    "doors.sfx.entities.grumble_roam3":{"sounds":["doors/sfx/entities/grumble_roam3"]},
    "doors.sfx.entities.grumble_roam4":{"sounds":["doors/sfx/entities/grumble_roam4"]},
    "doors.sfx.entities.grumble_roam5":{"sounds":["doors/sfx/entities/grumble_roam5"]},
    "doors.sfx.entities.grumble_roam6":{"sounds":["doors/sfx/entities/grumble_roam6"]},
    "doors.sfx.entities.grumble_roam7":{"sounds":["doors/sfx/entities/grumble_roam7"]},
    "doors.sfx.entities.grumble_roam8":{"sounds":["doors/sfx/entities/grumble_roam8"]},
    "doors.sfx.entities.grumble_roam9":{"sounds":["doors/sfx/entities/grumble_roam9"]},
    "doors.sfx.entities.grumble_roam10":{"sounds":["doors/sfx/entities/grumble_roam10"]},
    "doors.sfx.entities.grumble_roam11":{"sounds":["doors/sfx/entities/grumble_roam11"]},
    "doors.sfx.entities.grumble_roam12":{"sounds":["doors/sfx/entities/grumble_roam12"]},
    "doors.sfx.entities.grumble_roam13":{"sounds":["doors/sfx/entities/grumble_roam13"]},
    "doors.sfx.entities.grumble_roam14":{"sounds":["doors/sfx/entities/grumble_roam14"]},
    "doors.sfx.entities.grumble_roam15":{"sounds":["doors/sfx/entities/grumble_roam15"]},
    "doors.sfx.entities.grumble_roam16":{"sounds":["doors/sfx/entities/grumble_roam16"]},
    "doors.sfx.entities.grumble_roam17":{"sounds":["doors/sfx/entities/grumble_roam17"]},
    "doors.sfx.entities.grumble_roam18":{"sounds":["doors/sfx/entities/grumble_roam18"]},
    "doors.sfx.entities.grumble_roam19":{"sounds":["doors/sfx/entities/grumble_roam19"]},
    "doors.sfx.entities.grumble_roam20":{"sounds":["doors/sfx/entities/grumble_roam20"]},
    "doors.sfx.entities.grumble_roam21":{"sounds":["doors/sfx/entities/grumble_roam21"]},
    "doors.sfx.entities.grumble_roam22":{"sounds":["doors/sfx/entities/grumble_roam22"]},
    "doors.sfx.entities.grumble_roam23":{"sounds":["doors/sfx/entities/grumble_roam23"]},
    "doors.sfx.entities.grumble_roam24":{"sounds":["doors/sfx/entities/grumble_roam24"]},
    "doors.sfx.entities.grumble_roam25":{"sounds":["doors/sfx/entities/grumble_roam25"]},
    "doors.sfx.entities.grumble_roam26":{"sounds":["doors/sfx/entities/grumble_roam26"]},
    "doors.sfx.entities.grumble_roam27":{"sounds":["doors/sfx/entities/grumble_roam27"]},
    "doors.sfx.entities.grumble_roam28":{"sounds":["doors/sfx/entities/grumble_roam28"]},
    "doors.sfx.entities.grumble_roam29":{"sounds":["doors/sfx/entities/grumble_roam29"]},
    "doors.sfx.entities.grumble_roam30":{"sounds":["doors/sfx/entities/grumble_roam30"]},
    "doors.sfx.entities.grumble_roam31":{"sounds":["doors/sfx/entities/grumble_roam31"]},
    "doors.sfx.entities.grumble_roam32":{"sounds":["doors/sfx/entities/grumble_roam32"]},
    "doors.sfx.entities.grumble_roam33":{"sounds":["doors/sfx/entities/grumble_roam33"]},
    "doors.sfx.entities.grumble_roam34":{"sounds":["doors/sfx/entities/grumble_roam34"]},
    "doors.sfx.entities.grumble_roam35":{"sounds":["doors/sfx/entities/grumble_roam35"]},
    "doors.sfx.entities.grumble_roam36":{"sounds":["doors/sfx/entities/grumble_roam36"]},
    "doors.sfx.entities.grumble_roam37":{"sounds":["doors/sfx/entities/grumble_roam37"]},
    "doors.sfx.entities.grumble_roam38":{"sounds":["doors/sfx/entities/grumble_roam38"]},
    "doors.sfx.entities.grumble_roam39":{"sounds":["doors/sfx/entities/grumble_roam39"]},
    "doors.sfx.entities.grumble_roam40":{"sounds":["doors/sfx/entities/grumble_roam40"]},
    "doors.sfx.entities.grumble_roam41":{"sounds":["doors/sfx/entities/grumble_roam41"]},
    "doors.sfx.entities.grumble_roam42":{"sounds":["doors/sfx/entities/grumble_roam42"]},
    "doors.sfx.entities.grumble_roam43":{"sounds":["doors/sfx/entities/grumble_roam43"]},
    "doors.sfx.entities.grumble_roam44":{"sounds":["doors/sfx/entities/grumble_roam44"]},
    "doors.sfx.entities.grumble_roam45":{"sounds":["doors/sfx/entities/grumble_roam45"]},
    "doors.sfx.entities.grumble_roam46":{"sounds":["doors/sfx/entities/grumble_roam46"]},
    "doors.sfx.entities.grumble_roam47":{"sounds":["doors/sfx/entities/grumble_roam47"]},
    "doors.sfx.entities.grumble_roam48":{"sounds":["doors/sfx/entities/grumble_roam48"]},
    "doors.sfx.entities.grumble_roam49":{"sounds":["doors/sfx/entities/grumble_roam49"]},
    "doors.sfx.entities.grumble_roam50":{"sounds":["doors/sfx/entities/grumble_roam50"]},
    "doors.sfx.entities.grumble_roam51":{"sounds":["doors/sfx/entities/grumble_roam51"]},
    "doors.sfx.entities.grumble_roam52":{"sounds":["doors/sfx/entities/grumble_roam52"]},
    "doors.sfx.entities.grumble_roam53":{"sounds":["doors/sfx/entities/grumble_roam53"]},
    "doors.sfx.entities.grumble_roam54":{"sounds":["doors/sfx/entities/grumble_roam54"]},
    "doors.sfx.entities.grumble_roam55":{"sounds":["doors/sfx/entities/grumble_roam55"]},
    "doors.sfx.entities.grumble_roam56":{"sounds":["doors/sfx/entities/grumble_roam56"]},
    "doors.sfx.entities.grumble_roam57":{"sounds":["doors/sfx/entities/grumble_roam57"]},
    "doors.sfx.entities.grumble_roam58":{"sounds":["doors/sfx/entities/grumble_roam58"]},
    "doors.sfx.entities.grumble_roam59":{"sounds":["doors/sfx/entities/grumble_roam59"]},
    "doors.sfx.entities.grumble_roam60":{"sounds":["doors/sfx/entities/grumble_roam60"]},
    "doors.sfx.entities.grumble_roam61":{"sounds":["doors/sfx/entities/grumble_roam61"]},
    "doors.sfx.entities.grumble_roam62":{"sounds":["doors/sfx/entities/grumble_roam62"]},
    "doors.sfx.entities.grumble_roam63":{"sounds":["doors/sfx/entities/grumble_roam63"]},
    "doors.sfx.entities.grumble_roam64":{"sounds":["doors/sfx/entities/grumble_roam64"]},
    "doors.sfx.entities.grumble_roam65":{"sounds":["doors/sfx/entities/grumble_roam65"]},
    "doors.sfx.entities.grumble_roam66":{"sounds":["doors/sfx/entities/grumble_roam66"]},
    "doors.sfx.entities.grumble_roam67":{"sounds":["doors/sfx/entities/grumble_roam67"]},
    "doors.sfx.entities.grumble_roam68":{"sounds":["doors/sfx/entities/grumble_roam68"]},
    "doors.sfx.entities.grumble_roam69":{"sounds":["doors/sfx/entities/grumble_roam69"]},
    "doors.sfx.entities.grumble_roam70":{"sounds":["doors/sfx/entities/grumble_roam70"]},
    "doors.sfx.entities.grumble_roam71":{"sounds":["doors/sfx/entities/grumble_roam71"]},
    "doors.sfx.entities.grumble_roam72":{"sounds":["doors/sfx/entities/grumble_roam72"]},

    "doors.sfx.entities.seek_sewer_hand_spawn1":{"sounds":["doors/sfx/entities/seek_hand_spawn1"]},
    "doors.sfx.entities.seek_sewer_hand_spawn2":{"sounds":["doors/sfx/entities/seek_hand_spawn2"]},
    "doors.sfx.entities.seek_sewer_hand_spawn3":{"sounds":["doors/sfx/entities/seek_hand_spawn3"]},
    "doors.sfx.entities.seek_sewer_hand_spawn4":{"sounds":["doors/sfx/entities/seek_hand_spawn4"]},
    "doors.sfx.entities.seek_sewer_hand_spawn5":{"sounds":["doors/sfx/entities/seek_hand_spawn5"]},
    "doors.sfx.entities.seek_sewer_hand_spawn6":{"sounds":["doors/sfx/entities/seek_hand_spawn6"]},
    "doors.sfx.entities.seek_sewer_hand_spawn7":{"sounds":["doors/sfx/entities/seek_hand_spawn7"]},
    "doors.sfx.entities.seek_sewer_hand_spawn8":{"sounds":["doors/sfx/entities/seek_hand_spawn8"]},

    "doors.sfx.entities.seek_sewer_sludge_scream":{"sounds":["doors/sfx/entities/seek_sewer_sludge_scream"]},
    "doors.sfx.entities.seek_sewer_sludge_moving1":{"sounds":["doors/sfx/entities/seek_sewer_sludge_moving1"]},
    "doors.sfx.entities.seek_sewer_sludge_moving2":{"sounds":["doors/sfx/entities/seek_sewer_sludge_moving2"]},
    "doors.sfx.entities.seek_sewer_sludge_moving3":{"sounds":["doors/sfx/entities/seek_sewer_sludge_moving3"]},
    "doors.sfx.entities.seek_sewer_sludge_moving4":{"sounds":["doors/sfx/entities/seek_sewer_sludge_moving4"]},
    "doors.sfx.entities.seek_sewer_sludge_moving5":{"sounds":["doors/sfx/entities/seek_sewer_sludge_moving5"]},
    "doors.sfx.entities.seek_sewer_sludge_moving6":{"sounds":["doors/sfx/entities/seek_sewer_sludge_moving6"]},
    "doors.sfx.entities.seek_sewer_sludge_moving7":{"sounds":["doors/sfx/entities/seek_sewer_sludge_moving7"]},
    "doors.sfx.entities.seek_sewer_sludge_moving8":{"sounds":["doors/sfx/entities/seek_sewer_sludge_moving8"]},
    "doors.sfx.entities.seek_sewer_sludge_moving9":{"sounds":["doors/sfx/entities/seek_sewer_sludge_moving9"]},
    "doors.sfx.entities.seek_sewer_sludge_moving10":{"sounds":["doors/sfx/entities/seek_sewer_sludge_moving10"]},
    "doors.sfx.entities.seek_sewer_sludge_moving11":{"sounds":["doors/sfx/entities/seek_sewer_sludge_moving11"]},
    "doors.sfx.entities.seek_sewer_sludge_moving12":{"sounds":["doors/sfx/entities/seek_sewer_sludge_moving12"]},

    "doors.sfx.entities.seek_sewer_worm1":{"sounds":["doors/sfx/entities/seek_sewer_worm1"]},
    "doors.sfx.entities.seek_sewer_worm2":{"sounds":["doors/sfx/entities/seek_sewer_worm2"]},
    "doors.sfx.entities.seek_sewer_worm3":{"sounds":["doors/sfx/entities/seek_sewer_worm3"]},
    "doors.sfx.entities.seek_sewer_worm4":{"sounds":["doors/sfx/entities/seek_sewer_worm4"]},
    "doors.sfx.entities.seek_sewer_worm5":{"sounds":["doors/sfx/entities/seek_sewer_worm5"]},
    "doors.sfx.entities.seek_sewer_worm6":{"sounds":["doors/sfx/entities/seek_sewer_worm6"]},
    "doors.sfx.entities.seek_sewer_worm7":{"sounds":["doors/sfx/entities/seek_sewer_worm7"]},
    "doors.sfx.entities.seek_sewer_worm8":{"sounds":["doors/sfx/entities/seek_sewer_worm8"]},
    "doors.sfx.entities.seek_sewer_worm9":{"sounds":["doors/sfx/entities/seek_sewer_worm9"]},
    "doors.sfx.entities.seek_sewer_worm10":{"sounds":["doors/sfx/entities/seek_sewer_worm10"]},
    "doors.sfx.entities.seek_sewer_worm11":{"sounds":["doors/sfx/entities/seek_sewer_worm11"]},
    "doors.sfx.entities.seek_sewer_worm12":{"sounds":["doors/sfx/entities/seek_sewer_worm12"]},
    "doors.sfx.entities.seek_sewer_worm13":{"sounds":["doors/sfx/entities/seek_sewer_worm13"]},
    "doors.sfx.entities.seek_sewer_worm14":{"sounds":["doors/sfx/entities/seek_sewer_worm14"]},
    "doors.sfx.entities.seek_sewer_worm15":{"sounds":["doors/sfx/entities/seek_sewer_worm15"]},
    "doors.sfx.entities.seek_sewer_worm16":{"sounds":["doors/sfx/entities/seek_sewer_worm16"]},
    "doors.sfx.entities.seek_sewer_worm17":{"sounds":["doors/sfx/entities/seek_sewer_worm17"]},
    "doors.sfx.entities.seek_sewer_worm18":{"sounds":["doors/sfx/entities/seek_sewer_worm18"]},
    
    "doors.sfx.entities.seek_sewer_start":{"category":"music","sounds":["doors/sfx/entities/seek_sewer_start"]},
    "doors.sfx.entities.seek_sewer_flood":{"sounds":["doors/sfx/entities/seek_sewer_flood"]},
    "doors.sfx.entities.seek_sewer_lower":{"sounds":["doors/sfx/entities/seek_sewer_lower"]},
    "doors.sfx.entities.seek_sewer_scream":{"sounds":["doors/sfx/entities/seek_sewer_scream"]},
    "doors.sfx.entities.seek_sewer_hand_slap":{"sounds":["doors/sfx/entities/seek_sewer_hand_slap"]},

    "doors.sfx.entities.guiding_light_item_shimmer":{"category":"master","sounds":["doors/sfx/entities/guiding_light_item_shimmer"]},

    "doors.sfx.equipment.lighter_on":{"category":"master","sounds":["doors/sfx/equipment/lighter_on"]},
    "doors.sfx.equipment.lighter_off":{"category":"master","sounds":["doors/sfx/equipment/lighter_off"]},
    "doors.sfx.equipment.crucifix_use_success":{"category":"master","sounds":["doors/sfx/equipment/crucifix_use_success"]},
    "doors.sfx.equipment.crucifix_use_fail":{"category":"master","sounds":["doors/sfx/equipment/crucifix_use_fail"]},
    "doors.sfx.equipment.flashlight_on":{"category":"master","sounds":["doors/sfx/equipment/flashlight_on"]},
    "doors.sfx.equipment.flashlight_off":{"category":"master","sounds":["doors/sfx/equipment/flashlight_off"]},
    "doors.sfx.equipment.flashlight_flick":{"category":"master","sounds":["doors/sfx/equipment/flashlight_flick"]},
    "doors.sfx.equipment.candle_equip":{"category":"master","sounds":["doors/sfx/equipment/candle_equip"]},
    "doors.sfx.equipment.possessed_candle_rift_create":{"category":"master","sounds":["doors/sfx/equipment/possessed_candle_rift_create"]},
    "doors.sfx.equipment.possessed_candle_die":{"category":"master","sounds":["doors/sfx/equipment/possessed_candle_die"]},
    "doors.sfx.equipment.key_pickup":{"category":"master","sounds":["doors/sfx/equipment/key_pickup"]},
    "doors.sfx.equipment.key_use":{"category":"master","sounds":["doors/sfx/equipment/key_use"]},
    "doors.sfx.equipment.alarm_clock_use":{"category":"master","sounds":["doors/sfx/equipment/alarm_clock_use"]},
    "doors.sfx.equipment.alarm_clock_ring":{"category":"master","sounds":["doors/sfx/equipment/alarm_clock_ring"]},
    "doors.sfx.equipment.vitamins_use":{"category":"master","sounds":["doors/sfx/equipment/vitamins_use"]},

    "doors.sfx.equipment.vial_of_starlight_use":{"category":"master","sounds":["doors/sfx/equipment/vial_of_starlight_use"]},
    "doors.sfx.equipment.bottle_of_starlight_use":{"category":"master","sounds":["doors/sfx/equipment/bottle_of_starlight_use"]},
    "doors.sfx.equipment.barrel_of_starlight_use":{"category":"master","sounds":["doors/sfx/equipment/barrel_of_starlight_use"]},
    
    "doors.sfx.doors.hotel_door_open":{"category":"master","sounds":["doors/sfx/doors/hotel_door_open"]},
    "doors.sfx.doors.skeleton_key_door_open":{"category":"master","sounds":["doors/sfx/doors/skeleton_key_door_open"]},
    

    "doors.sfx.player.damage":{"category":"master","sounds":["doors/sfx/player/damage"]},
    "doors.sfx.player.death":{"category":"master","sounds":["doors/sfx/player/death"]},
    "doors.sfx.player.ringing":{"category":"master","sounds":["doors/sfx/player/ringing"]},
    "doors.sfx.player.heartbeat":{"category":"master","sounds":["doors/sfx/player/heartbeat"]},
    "doors.sfx.player.gold_increase":{"category":"master","sounds":["doors/sfx/player/gold_increase"]},
    "doors.sfx.player.gold_decrease":{"category":"master","sounds":["doors/sfx/player/gold_decrease"]},

    "doors.sfx.minecart.hit":{"category":"master","sounds":["doors/sfx/minecart/hit"]},
    "doors.sfx.minecart.lean_center":{"category":"master","sounds":["doors/sfx/minecart/lean_center"]},
    "doors.sfx.minecart.lean_left":{"category":"master","sounds":["doors/sfx/minecart/lean_left"]},
    "doors.sfx.minecart.lean_right":{"category":"master","sounds":["doors/sfx/minecart/lean_right"]},

    "doors.sfx.ambience.rooms":{"category":"ambient","sounds":["doors/sfx/ambience/rooms"]},

    "doors.sfx.ambience.fnaf_2_hallway":{"category":"ambient","sounds":["doors/sfx/ambience/fnaf_2_hallway"]},
    
    "doors.sfx.ambience.light_buzz":{"category":"ambient","sounds":["doors/sfx/ambience/light_buzz"]},
    "doors.sfx.ambience.light_buzz_stereo":{"category":"ambient","sounds":["doors/sfx/ambience/light_buzz_stereo"]},

    "doors.sfx.ambience.greenhouse":{"category":"ambient","sounds":["doors/sfx/ambience/greenhouse"]}
}